LICENSE.rst
setup.cfg
setup.py
src/pypalert/__init__.py
src/pypalert/mode1.py
src/pypalert/pypalert.py
src/pypalert.egg-info/PKG-INFO
src/pypalert.egg-info/SOURCES.txt
src/pypalert.egg-info/dependency_links.txt
src/pypalert.egg-info/top_level.txt