Metadata-Version: 2.1
Name: pypalert
Version: 2.1.1
Summary: A library can get Sanlien S303 modbus & mode 1 
Home-page: 
Author: sanlien
Author-email: paul_chen@sanlien.com
License: MIT
Keywords: S303 modbus
License-File: LICENSE.rst
